<annotation>
	<folder>Optisk</folder>
	<filename>190619_140226.jpg</filename>
	<path>C:\Users\Amalie Kolsgaard\Desktop\Fordypningsprosjekt_Autosit\Dataset\Optisk\190619_140226.jpg</path>
	<source>
		<database>Unknown</database>
	</source>
	<size>
		<width>4000</width>
		<height>3000</height>
		<depth>3</depth>
	</size>
	<segmented>0</segmented>
	<object>
		<name>motorboat with priority</name>
		<pose>Unspecified</pose>
		<truncated>0</truncated>
		<difficult>0</difficult>
		<bndbox>
			<xmin>1389</xmin>
			<ymin>863</ymin>
			<xmax>3207</xmax>
			<ymax>2635</ymax>
		</bndbox>
	</object>
	<object>
		<name>back</name>
		<pose>Unspecified</pose>
		<truncated>0</truncated>
		<difficult>0</difficult>
		<bndbox>
			<xmin>2070</xmin>
			<ymin>1977</ymin>
			<xmax>3205</xmax>
			<ymax>2577</ymax>
		</bndbox>
	</object>
	<object>
		<name>side</name>
		<pose>Unspecified</pose>
		<truncated>0</truncated>
		<difficult>0</difficult>
		<bndbox>
			<xmin>1505</xmin>
			<ymin>1971</ymin>
			<xmax>2061</xmax>
			<ymax>2615</ymax>
		</bndbox>
	</object>
	<object>
		<name>overbygg</name>
		<pose>Unspecified</pose>
		<truncated>0</truncated>
		<difficult>1</difficult>
		<bndbox>
			<xmin>1392</xmin>
			<ymin>1509</ymin>
			<xmax>1689</xmax>
			<ymax>1856</ymax>
		</bndbox>
	</object>
	<object>
		<name>mast</name>
		<pose>Unspecified</pose>
		<truncated>0</truncated>
		<difficult>0</difficult>
		<bndbox>
			<xmin>2048</xmin>
			<ymin>956</ymin>
			<xmax>2251</xmax>
			<ymax>1356</ymax>
		</bndbox>
	</object>
	<object>
		<name>mast</name>
		<pose>Unspecified</pose>
		<truncated>0</truncated>
		<difficult>0</difficult>
		<bndbox>
			<xmin>2264</xmin>
			<ymin>968</ymin>
			<xmax>2376</xmax>
			<ymax>1265</ymax>
		</bndbox>
	</object>
	<object>
		<name>wake back back</name>
		<pose>Unspecified</pose>
		<truncated>0</truncated>
		<difficult>0</difficult>
		<bndbox>
			<xmin>2083</xmin>
			<ymin>2584</ymin>
			<xmax>3276</xmax>
			<ymax>2706</ymax>
		</bndbox>
	</object>
	<object>
		<name>wake front back</name>
		<pose>Unspecified</pose>
		<truncated>0</truncated>
		<difficult>0</difficult>
		<bndbox>
			<xmin>1364</xmin>
			<ymin>2562</ymin>
			<xmax>1639</xmax>
			<ymax>2621</ymax>
		</bndbox>
	</object>
</annotation>
