<annotation>
	<folder>Optisk</folder>
	<filename>190619_071213.jpg</filename>
	<path>C:\Users\Amalie Kolsgaard\Desktop\Fordypningsprosjekt_Autosit\Dataset\Optisk\190619_071213.jpg</path>
	<source>
		<database>Unknown</database>
	</source>
	<size>
		<width>4000</width>
		<height>3000</height>
		<depth>3</depth>
	</size>
	<segmented>0</segmented>
	<object>
		<name>building</name>
		<pose>Unspecified</pose>
		<truncated>1</truncated>
		<difficult>0</difficult>
		<bndbox>
			<xmin>1</xmin>
			<ymin>1</ymin>
			<xmax>2875</xmax>
			<ymax>1744</ymax>
		</bndbox>
	</object>
	<object>
		<name>building</name>
		<pose>Unspecified</pose>
		<truncated>1</truncated>
		<difficult>0</difficult>
		<bndbox>
			<xmin>2870</xmin>
			<ymin>269</ymin>
			<xmax>4000</xmax>
			<ymax>1988</ymax>
		</bndbox>
	</object>
	<object>
		<name>building</name>
		<pose>Unspecified</pose>
		<truncated>0</truncated>
		<difficult>0</difficult>
		<bndbox>
			<xmin>3226</xmin>
			<ymin>6</ymin>
			<xmax>3756</xmax>
			<ymax>270</ymax>
		</bndbox>
	</object>
	<object>
		<name>building</name>
		<pose>Unspecified</pose>
		<truncated>0</truncated>
		<difficult>1</difficult>
		<bndbox>
			<xmin>3676</xmin>
			<ymin>217</ymin>
			<xmax>3853</xmax>
			<ymax>273</ymax>
		</bndbox>
	</object>
	<object>
		<name>building</name>
		<pose>Unspecified</pose>
		<truncated>0</truncated>
		<difficult>0</difficult>
		<bndbox>
			<xmin>2650</xmin>
			<ymin>235</ymin>
			<xmax>2873</xmax>
			<ymax>473</ymax>
		</bndbox>
	</object>
	<object>
		<name>building</name>
		<pose>Unspecified</pose>
		<truncated>0</truncated>
		<difficult>0</difficult>
		<bndbox>
			<xmin>2629</xmin>
			<ymin>123</ymin>
			<xmax>3188</xmax>
			<ymax>270</ymax>
		</bndbox>
	</object>
	<object>
		<name>building</name>
		<pose>Unspecified</pose>
		<truncated>1</truncated>
		<difficult>0</difficult>
		<bndbox>
			<xmin>2329</xmin>
			<ymin>1</ymin>
			<xmax>2604</xmax>
			<ymax>264</ymax>
		</bndbox>
	</object>
	<object>
		<name>building</name>
		<pose>Unspecified</pose>
		<truncated>1</truncated>
		<difficult>0</difficult>
		<bndbox>
			<xmin>1898</xmin>
			<ymin>1</ymin>
			<xmax>2308</xmax>
			<ymax>182</ymax>
		</bndbox>
	</object>
	<object>
		<name>building</name>
		<pose>Unspecified</pose>
		<truncated>1</truncated>
		<difficult>0</difficult>
		<bndbox>
			<xmin>432</xmin>
			<ymin>1</ymin>
			<xmax>1979</xmax>
			<ymax>461</ymax>
		</bndbox>
	</object>
	<object>
		<name>building</name>
		<pose>Unspecified</pose>
		<truncated>1</truncated>
		<difficult>0</difficult>
		<bndbox>
			<xmin>1</xmin>
			<ymin>1</ymin>
			<xmax>532</xmax>
			<ymax>461</ymax>
		</bndbox>
	</object>
	<object>
		<name>building</name>
		<pose>Unspecified</pose>
		<truncated>1</truncated>
		<difficult>1</difficult>
		<bndbox>
			<xmin>94</xmin>
			<ymin>1</ymin>
			<xmax>917</xmax>
			<ymax>129</ymax>
		</bndbox>
	</object>
	<object>
		<name>building</name>
		<pose>Unspecified</pose>
		<truncated>1</truncated>
		<difficult>0</difficult>
		<bndbox>
			<xmin>882</xmin>
			<ymin>1</ymin>
			<xmax>1376</xmax>
			<ymax>114</ymax>
		</bndbox>
	</object>
	<object>
		<name>building</name>
		<pose>Unspecified</pose>
		<truncated>1</truncated>
		<difficult>1</difficult>
		<bndbox>
			<xmin>3094</xmin>
			<ymin>1</ymin>
			<xmax>4000</xmax>
			<ymax>150</ymax>
		</bndbox>
	</object>
	<object>
		<name>building</name>
		<pose>Unspecified</pose>
		<truncated>1</truncated>
		<difficult>1</difficult>
		<bndbox>
			<xmin>3950</xmin>
			<ymin>79</ymin>
			<xmax>4000</xmax>
			<ymax>266</ymax>
		</bndbox>
	</object>
	<object>
		<name>motorboat with priority</name>
		<pose>Unspecified</pose>
		<truncated>0</truncated>
		<difficult>0</difficult>
		<bndbox>
			<xmin>536</xmin>
			<ymin>802</ymin>
			<xmax>3520</xmax>
			<ymax>2289</ymax>
		</bndbox>
	</object>
	<object>
		<name>back</name>
		<pose>Unspecified</pose>
		<truncated>0</truncated>
		<difficult>0</difficult>
		<bndbox>
			<xmin>3251</xmin>
			<ymin>1812</ymin>
			<xmax>3458</xmax>
			<ymax>2271</ymax>
		</bndbox>
	</object>
	<object>
		<name>side</name>
		<pose>Unspecified</pose>
		<truncated>0</truncated>
		<difficult>0</difficult>
		<bndbox>
			<xmin>936</xmin>
			<ymin>1859</ymin>
			<xmax>3242</xmax>
			<ymax>2274</ymax>
		</bndbox>
	</object>
	<object>
		<name>front</name>
		<pose>Unspecified</pose>
		<truncated>0</truncated>
		<difficult>0</difficult>
		<bndbox>
			<xmin>544</xmin>
			<ymin>1800</ymin>
			<xmax>945</xmax>
			<ymax>2202</ymax>
		</bndbox>
	</object>
	<object>
		<name>overbygg</name>
		<pose>Unspecified</pose>
		<truncated>0</truncated>
		<difficult>0</difficult>
		<bndbox>
			<xmin>939</xmin>
			<ymin>1524</ymin>
			<xmax>1460</xmax>
			<ymax>1857</ymax>
		</bndbox>
	</object>
	<object>
		<name>mast</name>
		<pose>Unspecified</pose>
		<truncated>0</truncated>
		<difficult>0</difficult>
		<bndbox>
			<xmin>1298</xmin>
			<ymin>824</ymin>
			<xmax>1438</xmax>
			<ymax>1490</ymax>
		</bndbox>
	</object>
	<object>
		<name>overbygg</name>
		<pose>Unspecified</pose>
		<truncated>0</truncated>
		<difficult>0</difficult>
		<bndbox>
			<xmin>1952</xmin>
			<ymin>1593</ymin>
			<xmax>2921</xmax>
			<ymax>1819</ymax>
		</bndbox>
	</object>
</annotation>
